funpymodeling/__init__.py
funpymodeling/data_prep.py
funpymodeling/exploratory.py
funpymodeling/model_validation.py
funpymodeling/test/__init__.py
funpymodeling/test/test_funpymodeling.py
funpymodeling-0.1.9.dist-info/METADATA
funpymodeling-0.1.9.dist-info/WHEEL
funpymodeling-0.1.9.dist-info/RECORD
